quine/meta/__init__.py
quine-0.0.2.dist-info/COPYING.md
quine-0.0.2.dist-info/METADATA
quine-0.0.2.dist-info/WHEEL
quine-0.0.2.dist-info/RECORD
